<annotation>
	<folder>Photos</folder>
	<filename>IMG_20190906_104155.jpg</filename>
	<path>D:\NECTEC\EST\Photos\IMG_20190906_104155.jpg</path>
	<source>
		<database>Unknown</database>
	</source>
	<size>
		<width>2976</width>
		<height>3968</height>
		<depth>3</depth>
	</size>
	<segmented>0</segmented>
	<object>
		<name>totoro</name>
		<pose>Unspecified</pose>
		<truncated>0</truncated>
		<difficult>0</difficult>
		<bndbox>
			<xmin>1065</xmin>
			<ymin>1087</ymin>
			<xmax>2911</xmax>
			<ymax>2625</ymax>
		</bndbox>
	</object>
	<object>
		<name>nekobus</name>
		<pose>Unspecified</pose>
		<truncated>0</truncated>
		<difficult>0</difficult>
		<bndbox>
			<xmin>236</xmin>
			<ymin>1687</ymin>
			<xmax>836</xmax>
			<ymax>2299</ymax>
		</bndbox>
	</object>
</annotation>
